{
    "usuarios": [
        {
            "id_usuario": "JT22859",
            "primer_nombre": "Jhojann",
            "segundo_nombre": "Estiven",
            "primer_apellido": "Triana",
            "segundo_apellido": "Quiroga",
            "rol": "1",
            "cargo": "1",
            "coordinacion": "1",
            "horario": "1",
            "contrasena": "$2a$10$LVGFtQtjAmUvARz/x1SOy.dSKUx1zjPP5yVnapsx0Peg5w.Vrk4v2"
        },
        {
            "id_usuario": "FJ64045",
            "primer_nombre": "Felipe",
            "segundo_nombre": "Alejandro",
            "primer_apellido": "Jimenez",
            "segundo_apellido": "Rodriguez",
            "rol": "1",
            "cargo": "1",
            "coordinacion": "1",
            "horario": "1",
            "contrasena": "$2a$10$LVGFtQtjAmUvARz/x1SOy.dSKUx1zjPP5yVnapsx0Peg5w.Vrk4v2"
        },
        {
            "id_usuario": "hola",
            "primer_nombre": "hola",
            "segundo_nombre": "hola",
            "primer_apellido": "hola",
            "segundo_apellido": "hola",
            "rol": "value1",
            "cargo": "value1",
            "coordinacion": "value1",
            "horario": "value1",
            "contrasena": "$2a$10$uQTs4OxbSQa6WMhSNdhAeObGc9NkFQ12G.vOPX.KsBc8Uj9YiZFoW"
        },
        {
            "id_usuario": "hola",
            "primer_nombre": "hola",
            "segundo_nombre": "hola",
            "primer_apellido": "hola",
            "segundo_apellido": "hola",
            "rol": "value1",
            "cargo": "value1",
            "coordinacion": "value1",
            "horario": "value1",
            "contrasena": "$2a$10$A4cd2JnnV4xu274JJAMETuM/9FQH/Gz8eMEff/EIFhgLSczaEnITS"
        }
    ]
}